sc2monitor/__init__.py
sc2monitor/controller.py
sc2monitor/handlers.py
sc2monitor/model.py
sc2monitor/sc2api.py
sc2monitor-0.2.13.dist-info/LICENSE
sc2monitor-0.2.13.dist-info/METADATA
sc2monitor-0.2.13.dist-info/WHEEL
sc2monitor-0.2.13.dist-info/top_level.txt
sc2monitor-0.2.13.dist-info/RECORD
