Metadata-Version: 2.1
Name: sc2monitor
Version: 0.2.13
Summary: When executed regularly keeps track of medium amount of StarCraft 2 accounts on the 1vs1 ladder
Home-page: https://github.com/2press/sc2monitor
Author: pressure
Author-email: pres.sure@ymail.com
License: MIT
Platform: UNKNOWN
Requires-Python: >=3.7.1
Requires-Dist: PyMySQL (>=0.9.3)
Requires-Dist: aiohttp (>=3.5.2)
Requires-Dist: sqlalchemy (>=1.2.15)
